<bills>
<bill id="547f40b81" sscode="CA15">
<number>
<session>2015-2016</session>
  <code>CA</code>
  <type>AB</type>
  <number>33</number>
</number>
<hearings></hearings>
<profiles>
<profile id="52d45db620d" status="tracking">
  <pname><![CDATA[ Poet|Profile|greenhouse gas]]></pname>
<keywords>
  <keyword><![CDATA[greenhouse gas]]></keyword>
  </keywords>
</profile>
</profiles>
</bill>
<bill id="54f1b825211d" sscode="CA15">
<number>
<session>2015-2016</session>
  <code>CA</code>
  <type>AB</type>
  <number>1110</number>
</number>
<hearings></hearings>
<profiles>
<profile id="56e71f931f8" status="tracking">
  <pname><![CDATA[ Enhanced|General|Renewable Energy]]></pname>
<keywords>
  <keyword><![CDATA[credits]]></keyword>
  <keyword><![CDATA[renewable energy]]></keyword>
  </keywords>
</profile>
</profiles>
</bill>
<bill id="54f1b82e1" sscode="CA15">
<number>
<session>2015-2016</session>
  <code>CA</code>
  <type>AB</type>
  <number>1114</number>
</number>
<hearings></hearings>
<profiles>
<profile id="4f3164841f" status="tracking">
  <pname><![CDATA[ Astellas|Healthcare General|Change in Reimbursement for Medicaid]]></pname>
<keywords>
  <keyword><![CDATA[medi-cal]]></keyword>
  <keyword><![CDATA[medicaid]]></keyword>
  <keyword><![CDATA[pharmacist]]></keyword>
  <keyword><![CDATA[pharmacists]]></keyword>
  <keyword><![CDATA[pharmacy]]></keyword>
  </keywords>
</profile>
<profile id="4f31651511a" status="tracking">
  <pname><![CDATA[ Astellas|Healthcare General|Healthcare Exchanges]]></pname>
<keywords>
  <keyword><![CDATA[health care]]></keyword>
  </keywords>
</profile>
<profile id="4f316523110" status="tracking">
  <pname><![CDATA[ Astellas|Healthcare General|Healthcare Reform]]></pname>
<keywords>
  <keyword><![CDATA[health care reform]]></keyword>
  </keywords>
</profile>
<profile id="5739e9cd1b9e" status="tracking">
  <pname><![CDATA[ Xtend|General|Medicaid Billing]]></pname>
<keywords>
  <keyword><![CDATA[bill]]></keyword>
  <keyword><![CDATA[billing]]></keyword>
  <keyword><![CDATA[medi-cal]]></keyword>
  </keywords>
</profile>
</profiles>
</bill>
<bill id="54f1b9c41" sscode="CA15">
<number>
<session>2015-2016</session>
  <code>CA</code>
  <type>AB</type>
  <number>1289</number>
</number>
<hearings></hearings>
<profiles>
<profile id="56746d41985" status="tracking">
  <pname><![CDATA[ TIA|General Issues|Data Breach]]></pname>
<keywords>
  <keyword><![CDATA[identity theft]]></keyword>
  </keywords>
</profile>
<profile id="5679df0717de" status="tracking">
  <pname><![CDATA[ TIA|General Issues|Disruptor]]></pname>
<keywords>
  <keyword><![CDATA[charter-party carriers]]></keyword>
  <keyword><![CDATA[independent contractor]]></keyword>
  <keyword><![CDATA[transportation network companies]]></keyword>
  <keyword><![CDATA[transportation network company]]></keyword>
  </keywords>
</profile>
</profiles>
</bill>
<bill id="568f6da9773" sscode="CA15">
<number>
<session>2015-2016</session>
  <code>CA</code>
  <type>AB</type>
  <number>1637</number>
</number>
<hearings></hearings>
<profiles>
<profile id="52d45d9820d" status="tracking">
  <pname><![CDATA[ Poet|Profile|anti-ethanol and renewable fuel standard]]></pname>
<keywords>
  <keyword><![CDATA[fuel]]></keyword>
  <keyword><![CDATA[quality standards]]></keyword>
  </keywords>
</profile>
<profile id="52d45db620d" status="tracking">
  <pname><![CDATA[ Poet|Profile|greenhouse gas]]></pname>
<keywords>
  <keyword><![CDATA[fuel]]></keyword>
  <keyword><![CDATA[greenhouse gas]]></keyword>
  </keywords>
</profile>
</profiles>
</bill>
<bill id="54a500992" sscode="CA15">
<number>
<session>2015-2016</session>
  <code>CA</code>
  <type>SB</type>
  <number>62</number>
</number>
<hearings></hearings>
<profiles>
<profile id="548b14b5212" status="tracking">
  <pname><![CDATA[ Navient|Business|Servicemembers Benefits]]></pname>
<keywords>
  <keyword><![CDATA[collecting]]></keyword>
  <keyword><![CDATA[loan]]></keyword>
  <keyword><![CDATA[loans]]></keyword>
  <keyword><![CDATA[military]]></keyword>
  </keywords>
</profile>
<profile id="548b16eb1b" status="tracking">
  <pname><![CDATA[ Navient|Business|Student Loans]]></pname>
<keywords>
  <keyword><![CDATA[student loan]]></keyword>
  </keywords>
</profile>
</profiles>
</bill>
<bill id="56c6cbbd1a5" sscode="CA15">
<number>
<session>2015-2016</session>
  <code>CA</code>
  <type>SB</type>
  <number>1222</number>
</number>
<hearings></hearings>
<profiles>
<profile id="56e71f931f8" status="tracking">
  <pname><![CDATA[ Enhanced|General|Renewable Energy]]></pname>
<keywords>
  <keyword><![CDATA[credit]]></keyword>
  <keyword><![CDATA[credits]]></keyword>
  <keyword><![CDATA[renewable energy]]></keyword>
  </keywords>
</profile>
<profile id="52d45db620d" status="tracking">
  <pname><![CDATA[ Poet|Profile|greenhouse gas]]></pname>
<keywords>
  <keyword><![CDATA[fuel]]></keyword>
  <keyword><![CDATA[greenhouse gas]]></keyword>
  </keywords>
</profile>
<profile id="56746d41985" status="tracking">
  <pname><![CDATA[ TIA|General Issues|Data Breach]]></pname>
<keywords>
  <keyword><![CDATA[cyber]]></keyword>
  <keyword><![CDATA[cyber security]]></keyword>
  </keywords>
</profile>
<profile id="5679df0717de" status="tracking">
  <pname><![CDATA[ TIA|General Issues|Disruptor]]></pname>
<keywords>
  <keyword><![CDATA[california public utilities commission]]></keyword>
  <keyword><![CDATA[charter-party carrier]]></keyword>
  <keyword><![CDATA[charter-party carriers]]></keyword>
  <keyword><![CDATA[transportation network company]]></keyword>
  </keywords>
</profile>
</profiles>
</bill>
</bills>
